hackernote/__init__.py
hackernote/__main__.py
hackernote/error/__init__.py
hackernote/parser/__init__.py
hackernote/util/__init__.py
tests/__init__.py
hackernote-0.0.2.dist-info/LICENSE
hackernote-0.0.2.dist-info/METADATA
hackernote-0.0.2.dist-info/WHEEL
hackernote-0.0.2.dist-info/entry_points.txt
hackernote-0.0.2.dist-info/top_level.txt
hackernote-0.0.2.dist-info/RECORD
