Metadata-Version: 2.1
Name: hackernote
Version: 0.0.2
Summary: Reference library to parse and render hackernotes
Home-page: https://github.com/pyrustic/hackernote
Author: Pyrustic Evangelist
Author-email: rusticalex@yahoo.com
Maintainer: Pyrustic Evangelist
Maintainer-email: rusticalex@yahoo.com
License: MIT
Keywords: library,hackernote,hkn,parser,renderer,file-format
Platform: UNKNOWN
Classifier: Programming Language :: Python :: 3
Classifier: License :: OSI Approved :: MIT License
Classifier: Operating System :: OS Independent
Requires-Python: >=3.5
License-File: LICENSE
